KappaNEURON/__init__.py
KappaNEURON/tests/__init__.py
KappaNEURON/tests/caMinimal.ka
KappaNEURON/tests/caPump1.ka
KappaNEURON/tests/caPump1.mod
KappaNEURON/tests/caPump2.ka
KappaNEURON/tests/caPump2.mod
KappaNEURON/tests/capulse.mod
KappaNEURON/tests/glupulse.mod
KappaNEURON/tests/napulse.ka
KappaNEURON/tests/napulse.mod
KappaNEURON/tests/nmda.ka
KappaNEURON/tests/nrnivmodl.py
KappaNEURON-0.3.2.dist-info/METADATA
KappaNEURON-0.3.2.dist-info/RECORD
KappaNEURON-0.3.2.dist-info/WHEEL
KappaNEURON-0.3.2.dist-info/top_level.txt
