Metadata-Version: 2.1
Name: KappaNEURON
Version: 0.3.2
Summary: KappaNEURON integrates the SpatialKappa simulator with NEURON to allow rule-based simulations of molecular systems embedded in neurons.
Home-page: https://github.com/davidcsterratt/KappaNEURON
Author: David C Sterratt
Author-email: david.c.sterratt@ed.ac.uk
License: UNKNOWN
Platform: UNKNOWN
Classifier: Programming Language :: Python :: 2
Classifier: License :: OSI Approved :: GNU General Public License v3 (GPLv3)
Classifier: Operating System :: OS Independent
Requires-Python: <3
Requires-Dist: SpatialKappa (>=2.1.5)
Requires-Dist: SciPy
Requires-Dist: matplotlib (<3.0)
